cmd_calc/__main__.py
space_coder_cmd_calc-1.3.1.dist-info/METADATA
space_coder_cmd_calc-1.3.1.dist-info/WHEEL
space_coder_cmd_calc-1.3.1.dist-info/entry_points.txt
space_coder_cmd_calc-1.3.1.dist-info/top_level.txt
space_coder_cmd_calc-1.3.1.dist-info/RECORD
