Metadata-Version: 2.4
Name: space_-_coder-cmd-calc
Version: 1.3.1
Summary: A simple command line calculator
Author-email: Madhav Garg <gargm0325@wrdsb.ca>
Classifier: License :: OSI Approved :: MIT License
Classifier: Programming Language :: Python
Classifier: Programming Language :: Python :: 3
Requires-Python: >=3.9
Requires-Dist: pynput
Requires-Dist: colorama
